mcpuniverse/__init__.py
mcpuniverse/agent/__init__.py
mcpuniverse/agent/base.py
mcpuniverse/agent/basic.py
mcpuniverse/agent/claude_code.py
mcpuniverse/agent/depreciated_function_call.py
mcpuniverse/agent/explore_and_exploit.py
mcpuniverse/agent/function_call.py
mcpuniverse/agent/harmony_agent.py
mcpuniverse/agent/manager.py
mcpuniverse/agent/openai_agent_sdk.py
mcpuniverse/agent/react.py
mcpuniverse/agent/reflection.py
mcpuniverse/agent/types.py
mcpuniverse/agent/utils.py
mcpuniverse/agent/workflow.py
mcpuniverse/agent/configs/explore_and_exploit_prompt.j2
mcpuniverse/agent/configs/function_call_prompt.j2
mcpuniverse/agent/configs/openai_agent_sdk_prompt.j2
mcpuniverse/agent/configs/react_prompt.j2
mcpuniverse/agent/configs/reflection_prompt.j2
mcpuniverse/agent/configs/system_prompt.j2
mcpuniverse/agent/configs/tools_prompt.j2
mcpuniverse/agent/memory/__init__.py
mcpuniverse/agent/memory/base.py
mcpuniverse/agent/memory/short_term/__init__.py
mcpuniverse/agent/memory/short_term/ram.py
mcpuniverse/agent/memory/short_term/redis.py
mcpuniverse/app/__init__.py
mcpuniverse/app/main.py
mcpuniverse/app/server.py
mcpuniverse/app/api/__init__.py
mcpuniverse/app/api/benchmark.py
mcpuniverse/app/api/chat.py
mcpuniverse/app/api/job.py
mcpuniverse/app/api/middleware.py
mcpuniverse/app/api/project.py
mcpuniverse/app/api/task.py
mcpuniverse/app/api/user.py
mcpuniverse/app/core/__init__.py
mcpuniverse/app/core/engine.py
mcpuniverse/app/db/__init__.py
mcpuniverse/app/db/database.py
mcpuniverse/app/db/migration.py
mcpuniverse/app/db/migration/000001_init.down.sql
mcpuniverse/app/db/migration/000001_init.up.sql
mcpuniverse/app/db/sqlc/__init__.py
mcpuniverse/app/db/sqlc/benchmark.py
mcpuniverse/app/db/sqlc/benchmark_job.py
mcpuniverse/app/db/sqlc/models.py
mcpuniverse/app/db/sqlc/models_sqlalchemy.py
mcpuniverse/app/db/sqlc/project.py
mcpuniverse/app/db/sqlc/released_benchmark.py
mcpuniverse/app/db/sqlc/released_project.py
mcpuniverse/app/db/sqlc/released_task.py
mcpuniverse-1.0.4.dist-info/licenses/LICENSE.txt
mcpuniverse-1.0.4.dist-info/METADATA
mcpuniverse-1.0.4.dist-info/WHEEL
mcpuniverse-1.0.4.dist-info/top_level.txt
mcpuniverse-1.0.4.dist-info/RECORD
