Metadata-Version: 2.4
Name: mcpuniverse
Version: 1.0.4
Summary: A framework for developing and benchmarking AI agents using Model Context Protocol (MCP)
Author: Salesforce Research
License: Apache 2.0
Project-URL: Homepage, https://github.com/SalesforceAIResearch/MCP-Universe
Project-URL: Repository, https://github.com/SalesforceAIResearch/MCP-Universe
Keywords: AI,Agents,MCP,benchmarking,LLM,machine-learning
Classifier: Intended Audience :: Developers
Classifier: Programming Language :: Python :: 3
Classifier: Programming Language :: Python :: 3.10
Classifier: Programming Language :: Python :: 3.11
Classifier: Programming Language :: Python :: 3.12
Requires-Python: <4,>=3.10
License-File: LICENSE.txt
Requires-Dist: requests==2.32.4
Requires-Dist: pydantic==2.11.7
Requires-Dist: pydantic[email]==2.11.7
Requires-Dist: schema==0.7.7
Requires-Dist: mcp==1.13.1
Requires-Dist: httpx==0.28.1
Requires-Dist: click==8.1.8
Requires-Dist: jinja2==3.1.6
Requires-Dist: python-dotenv==1.0.1
Requires-Dist: anyio==4.9.0
Requires-Dist: openai==1.106.1
Requires-Dist: anthropic==0.49.0
Requires-Dist: mistralai==1.6.0
Requires-Dist: pyyaml==6.0.2
Requires-Dist: google-genai==1.16.1
Requires-Dist: redis==6.1.0
Requires-Dist: psycopg[binary]==3.2.9
Requires-Dist: sqlalchemy[asyncio]==2.0.41
Requires-Dist: fastapi==0.115.12
Requires-Dist: bcrypt==4.3.0
Requires-Dist: pyseto==1.8.4
Requires-Dist: celery==5.5.3
Requires-Dist: xai-sdk==1.0.0
Requires-Dist: claude-code-sdk==0.0.20
Requires-Dist: openai-agents==0.2.11
Requires-Dist: wikipedia-api==0.8.1
Requires-Dist: mcp_server_fetch
Requires-Dist: google-auth==2.38.0
Requires-Dist: google-auth-oauthlib==1.2.1
Requires-Dist: google-api-python-client
Requires-Dist: mcp_server_calculator==0.1.1
Requires-Dist: yfinance==0.2.61
Requires-Dist: blender-mcp==1.1.3
Requires-Dist: playwright==1.52.0
Requires-Dist: mathutils==3.3.0
Requires-Dist: uvicorn[standard]==0.34.0
Requires-Dist: pytz==2024.2
Requires-Dist: tiktoken==0.11.0
Requires-Dist: kafka-python==2.2.15
Requires-Dist: pika==1.3.2
Provides-Extra: dev
Requires-Dist: pytest; extra == "dev"
Requires-Dist: pytest-asyncio; extra == "dev"
Requires-Dist: pytest-postgresql; extra == "dev"
Requires-Dist: pylint; extra == "dev"
Requires-Dist: pre-commit; extra == "dev"
Provides-Extra: web
Requires-Dist: uvicorn[standard]==0.34.0; extra == "web"
Requires-Dist: fastapi==0.115.12; extra == "web"
Requires-Dist: celery==5.5.3; extra == "web"
Requires-Dist: redis==6.1.0; extra == "web"
Requires-Dist: psycopg[binary]==3.2.9; extra == "web"
Requires-Dist: sqlalchemy[asyncio]==2.0.41; extra == "web"
Provides-Extra: dashboard
Requires-Dist: gradio>=5.42.0; extra == "dashboard"
Dynamic: license-file
